gimmebio.pangea-0.2.8-py3.6-nspkg.pth
gimmebio/pangea/__init__.py
gimmebio/pangea/api.py
gimmebio/pangea/cli.py
gimmebio/pangea/constants.py
gimmebio/pangea/utils.py
gimmebio.pangea-0.2.8.dist-info/METADATA
gimmebio.pangea-0.2.8.dist-info/WHEEL
gimmebio.pangea-0.2.8.dist-info/namespace_packages.txt
gimmebio.pangea-0.2.8.dist-info/top_level.txt
gimmebio.pangea-0.2.8.dist-info/RECORD
